pwnkss/__init__.py
pwnkss/new.py
pwnkss-0.1.1.dist-info/entry_points.txt
pwnkss-0.1.1.dist-info/WHEEL
pwnkss-0.1.1.dist-info/METADATA
pwnkss-0.1.1.dist-info/RECORD
