Metadata-Version: 2.1
Name: pwnkss
Version: 0.1.1
Summary: Just a package built by pawan at TAI
Author: pawanniroula777
Author-email: pawanniroula777@gmail.com
Requires-Python: >=3.8,<4.0
Classifier: Programming Language :: Python :: 3
Classifier: Programming Language :: Python :: 3.10
Classifier: Programming Language :: Python :: 3.8
Classifier: Programming Language :: Python :: 3.9
Requires-Dist: requests (>=2.27.1,<3.0.0)
